tie_bcd_api_v2/Request.py
tie_bcd_api_v2/__init__.py
tie_bcd_api_v2/resources/Company.py
tie_bcd_api_v2/resources/__init__.py
tie_bcd_api_v2-0.0.1.dist-info/METADATA
tie_bcd_api_v2-0.0.1.dist-info/WHEEL
tie_bcd_api_v2-0.0.1.dist-info/top_level.txt
tie_bcd_api_v2-0.0.1.dist-info/RECORD
