Metadata-Version: 2.1
Name: tie-bcd-api-v2
Version: 0.0.1
Summary: TIE International Microsoft Business Central API
Author: Michael Schori
Author-email: <michael@tie-international.com
Keywords: python,microsoft,business,central,api,tie,international
Classifier: Development Status :: 1 - Planning
Classifier: Intended Audience :: Developers
Classifier: Programming Language :: Python :: 3
Classifier: Operating System :: MacOS :: MacOS X
Classifier: Operating System :: Microsoft :: Windows
Requires-Dist: requests
